cluey/__init__.py
cluey/cli.py
cluey/examples/__init__.py
cluey/examples/arithmetic.py
cluey/examples/extendedml.py
cluey/examples/greet.py
cluey/examples/ml.py
cluey/examples/productionml.py
cluey/examples/stringtools.py
cluey/testing.py
cluey-0.1.0.dist-info/LICENSE
cluey-0.1.0.dist-info/METADATA
cluey-0.1.0.dist-info/WHEEL
cluey-0.1.0.dist-info/entry_points.txt
cluey-0.1.0.dist-info/RECORD
