Metadata-Version: 2.3
Name: cluey
Version: 0.1.0
Summary: Build clever, class-based command line apps with minimal boilerplate.
License: Apache-2.0
Keywords: command-line interface
Author: Robert Turnbull
Author-email: robert.turnbull@unimelb.edu.au
Requires-Python: >=3.10,<4.0
Classifier: Intended Audience :: Science/Research
Classifier: License :: OSI Approved :: Apache Software License
Classifier: Programming Language :: Python :: 3
Classifier: Programming Language :: Python :: 3.10
Classifier: Programming Language :: Python :: 3.11
Classifier: Programming Language :: Python :: 3.12
Classifier: Programming Language :: Python :: 3.13
Classifier: Topic :: Scientific/Engineering :: Artificial Intelligence
Classifier: Topic :: Software Development :: Libraries :: Application Frameworks
Classifier: Topic :: Software Development :: Libraries :: Python Modules
Requires-Dist: rich (>=10.16.1)
Requires-Dist: typer (>=0.4.0)
Project-URL: Documentation, https://rbturnbull.github.io/cluey/
Project-URL: Homepage, https://github.com/rbturnbull/cluey
Project-URL: Repository, https://github.com/rbturnbull/cluey
